docktor/analyzer.py
docktor/benchmarker.py
docktor/cli.py
docktor/optimizer.py
docktor/parser.py
docktor/reporter.py
docktor/types.py
docktor/rules/base.py
docktor/rules/best_practices.py
docktor/rules/performance.py
docktor/rules/security.py
docktor_py-0.1.1.dist-info/licenses/LICENSE
docktor_py-0.1.1.dist-info/METADATA
docktor_py-0.1.1.dist-info/WHEEL
docktor_py-0.1.1.dist-info/entry_points.txt
docktor_py-0.1.1.dist-info/top_level.txt
docktor_py-0.1.1.dist-info/RECORD
