Metadata-Version: 2.4
Name: docktor-py
Version: 0.1.1
Summary: A smart Dockerfile linter, optimizer, and explainer.
Author-email: Nash Correia <nashco9900@gmail.com>
License: MIT License
Project-URL: Homepage, https://github.com/Nash0810/docktor
Project-URL: Bug Tracker, https://github.com/Nash0810/docktor/issues
Classifier: Development Status :: 4 - Beta
Classifier: Environment :: Console
Classifier: Intended Audience :: Developers
Classifier: License :: OSI Approved :: MIT License
Classifier: Operating System :: OS Independent
Classifier: Programming Language :: Python :: 3
Classifier: Programming Language :: Python :: 3.8
Classifier: Programming Language :: Python :: 3.9
Classifier: Programming Language :: Python :: 3.10
Classifier: Programming Language :: Python :: 3.11
Classifier: Topic :: Software Development :: Build Tools
Classifier: Topic :: Software Development :: Quality Assurance
Requires-Python: >=3.8
License-File: LICENSE
Requires-Dist: click>=8.1.0
Requires-Dist: rich>=13.0.0
Requires-Dist: chardet>=5.0.0
Requires-Dist: docker>=6.0.0
Requires-Dist: pypiwin32>=223; sys_platform == "win32"
Provides-Extra: dev
Requires-Dist: pytest>=7.0; extra == "dev"
Requires-Dist: pytest-cov>=4.0; extra == "dev"
Requires-Dist: mypy>=1.0; extra == "dev"
Requires-Dist: ruff>=0.1.0; extra == "dev"
Requires-Dist: build; extra == "dev"
Requires-Dist: twine; extra == "dev"
Dynamic: license-file
